jxc/__init__.py
jxc/composite.py
jxc/get_params.py
jxc/helper.cpython-313-darwin.so
jxc/libxc_aliases.py
jxc/maple_series_overrides.py
jxc/maple_taylor_overrides.py
jxc/_libxc/__init__.py
jxc/_libxc/core.py
jxc/_libxc/flags.py
jxc/_libxc/functional.py
jxc/_libxc/libxc.dylib
jxc/_libxc/structs.py
jxc/_libxc/util.py
jxc/derivatives/__init__.py
jxc/derivatives/_maple_derivs.py
jxc/derivatives/ad_derivs.py
jxc/derivatives/libxc_derivs.py
jxc/functionals/__init__.py
jxc/functionals/_libxc_laplacian.py
jxc/functionals/deorbitalized_common.py
jxc/functionals/gga_c_acgga.py
jxc/functionals/gga_c_acggap.py
jxc/functionals/gga_c_am05.py
jxc/functionals/gga_c_bmk.py
jxc/functionals/gga_c_ccdf.py
jxc/functionals/gga_c_chachiyo.py
jxc/functionals/gga_c_cs1.py
jxc/functionals/gga_c_ft97.py
jxc/functionals/gga_c_gapc.py
jxc/functionals/gga_c_gaploc.py
jxc/functionals/gga_c_hcth_a.py
jxc/functionals/gga_c_lm.py
jxc/functionals/gga_c_lyp.py
jxc/functionals/gga_c_lypr.py
jxc/functionals/gga_c_op_b88.py
jxc/functionals/gga_c_op_g96.py
jxc/functionals/gga_c_op_pbe.py
jxc/functionals/gga_c_op_pw91.py
jxc/functionals/gga_c_op_xalpha.py
jxc/functionals/gga_c_optc.py
jxc/functionals/gga_c_p86.py
jxc/functionals/gga_c_p86vwn.py
jxc/functionals/gga_c_pbe.py
jxc/functionals/gga_c_pbe_erf_gws.py
jxc/functionals/gga_c_pbe_vwn.py
jxc/functionals/gga_c_pbeloc.py
jxc/functionals/gga_c_pw91.py
jxc/functionals/gga_c_q2d.py
jxc/functionals/gga_c_regtpss.py
jxc/functionals/gga_c_revtca.py
jxc/functionals/gga_c_scan_e0.py
jxc/functionals/gga_c_sg4.py
jxc/functionals/gga_c_sogga11.py
jxc/functionals/gga_c_tca.py
jxc/functionals/gga_c_w94.py
jxc/functionals/gga_c_wi.py
jxc/functionals/gga_c_wl.py
jxc/functionals/gga_c_zpbeint.py
jxc/functionals/gga_c_zvpbeint.py
jxc/functionals/gga_c_zvpbeloc.py
jxc/functionals/gga_k_apbe.py
jxc/functionals/gga_k_apbeint.py
jxc/functionals/gga_k_dk.py
jxc/functionals/gga_k_exp4.py
jxc/functionals/gga_k_lc94.py
jxc/functionals/gga_k_lgap.py
jxc_python-0.1.12.dist-info/METADATA
jxc_python-0.1.12.dist-info/WHEEL
jxc_python-0.1.12.dist-info/top_level.txt
jxc_python-0.1.12.dist-info/RECORD
