Metadata-Version: 2.4
Name: jxc-python
Version: 0.1.12
Summary: JAX-based exchange-correlation functionals library
Requires-Python: <3.14,>=3.11
Requires-Dist: wheel>=0.37.0
Requires-Dist: setuptools==68.2.2
Requires-Dist: absl-py==2.1.0
Requires-Dist: jaxtyping>=0.2.0
Requires-Dist: numpy<3.0.0,>=2.0.0
Requires-Dist: scipy>=1.15.0
Requires-Dist: ml-dtypes>=0.5.0
Requires-Dist: opt-einsum>=3.4.0
Requires-Dist: jinja2>=3.0.0
Requires-Dist: matplotlib>=3.10.7
